wosplus/__init__.py
wosplus/_google_drive_tools.py
wosplus/_merge_tools.py
wosplus/_pajek_tools.py
wosplus/_plotter.py
wosplus/_wos_parser.py
wosplus/_wos_scp.py
wosplus/wosplus.py
WOSplus-0.2.11.dist-info/LICENSE.txt
WOSplus-0.2.11.dist-info/METADATA
WOSplus-0.2.11.dist-info/WHEEL
WOSplus-0.2.11.dist-info/top_level.txt
WOSplus-0.2.11.dist-info/RECORD
