Metadata-Version: 2.1
Name: WOSplus
Version: 0.2.11
Summary: WOS+ is a tool for to manage and merge bibliographic databases like Web Of Science or Scopus
Home-page: https://github.com/colav/WOSplus
Author: Diego Restrepo
Author-email: restrepo@udea.edu.co
License: BSD
Platform: UNKNOWN
Requires-Dist: configparser
Requires-Dist: xlrd
Requires-Dist: requests
Requires-Dist: numpy
Requires-Dist: pandas
Requires-Dist: unidecode
Requires-Dist: python-levenshtein
Requires-Dist: venn
